sg_series/__init__.py
sg_series/sequence_analyzer.py
sg_series-1.0.0.dist-info/licenses/LICENSE
sg_series-1.0.0.dist-info/METADATA
sg_series-1.0.0.dist-info/WHEEL
sg_series-1.0.0.dist-info/top_level.txt
sg_series-1.0.0.dist-info/RECORD
