Metadata-Version: 2.4
Name: sg_series
Version: 1.0.0
Summary: A comprehensive sequence analyzer with polynomial, geometric, logarithmic, and custom pattern detection.
Author-email: Shivang Gupta <shivang.gupta@users.noreply.github.com>
License: MIT License
Keywords: sequence,analysis,polynomial,geometric,logarithmic,prediction
Classifier: Programming Language :: Python :: 3
Classifier: License :: OSI Approved :: MIT License
Classifier: Operating System :: OS Independent
Requires-Python: >=3.8
License-File: LICENSE
Requires-Dist: numpy
Requires-Dist: matplotlib
Dynamic: license-file
